SprelfJSON/JSONDefinitions.py
SprelfJSON/JSONUtils.py
SprelfJSON/__init__.py
SprelfJSON/Helpers/ClassHelpers.py
SprelfJSON/Helpers/Decorators.py
SprelfJSON/Helpers/TimeHelpers.py
SprelfJSON/Helpers/YAMLHelpers.py
SprelfJSON/Helpers/__init__.py
SprelfJSON/JSONModel/JSONModel.py
SprelfJSON/JSONModel/JSONModelError.py
SprelfJSON/JSONModel/ModelElem.py
SprelfJSON/JSONModel/__init__.py
SprelfJSON/Objects/Ephemeral.py
SprelfJSON/Objects/__init__.py
sprelf_json-2025.10.13.0.dist-info/METADATA
sprelf_json-2025.10.13.0.dist-info/WHEEL
sprelf_json-2025.10.13.0.dist-info/top_level.txt
sprelf_json-2025.10.13.0.dist-info/RECORD
