Metadata-Version: 2.4
Name: sprelf-json
Version: 2025.10.13.0
Summary: Simplifies defining schema for and managing JSON objects with non-JSON types
Author-email: Christopher Dilley <christopher@cabuu.de>
License-Expression: MIT
Project-URL: repository, https://github.com/cgdilley/SprelfJSON
Classifier: Programming Language :: Python :: 3
Classifier: Operating System :: OS Independent
Requires-Python: >=3.11
Requires-Dist: typing-inspect
Provides-Extra: yaml
Requires-Dist: ruamel.yaml; extra == "yaml"
